LICENSE
README.md
setup.cfg
setup.py
pyiikoapi/__init__.py
pyiikoapi.egg-info/PKG-INFO
pyiikoapi.egg-info/SOURCES.txt
pyiikoapi.egg-info/dependency_links.txt
pyiikoapi.egg-info/not-zip-safe
pyiikoapi.egg-info/requires.txt
pyiikoapi.egg-info/top_level.txt
pyiikoapi/biz/__init__.py
pyiikoapi/biz/api.py
pyiikoapi/biz/exception.py
pyiikoapi/card/__init__.py
pyiikoapi/card/api.py
pyiikoapi/card/exception.py