Metadata-Version: 2.1
Name: pyiikoapi
Version: 0.0.10
Summary: Python services for convenient work with iiko Biz API and iiko Card API
Home-page: UNKNOWN
Author: kebrick
Author-email: ruban.kebr@gmail.com
License: MIT
Project-URL: Source, https://github.com/kebrick/pyiikoapi
Project-URL: Tracker, https://github.com/kebrick/pyiikoapi/issues
Platform: UNKNOWN
Requires-Python: >=3
License-File: LICENSE
